translatify
